README
setup.py
deepstacks/__init__.py
deepstacks/fields.py
deepstacks/macros.py
deepstacks/stacked.py
deepstacks.egg-info/PKG-INFO
deepstacks.egg-info/SOURCES.txt
deepstacks.egg-info/dependency_links.txt
deepstacks.egg-info/top_level.txt
tests/__init__.py
tests/runall.py
tests/test0.py